{"_type":"export","__export_format":4,"__export_date":"2023-06-04T11:09:04.239Z","__export_source":"insomnia.desktop.app:v2023.2.2","resources":[{"_id":"req_37fc545dffb34779822afdebf15dee7b","parentId":"wrk_8e8c71d4ad08446faea254f3d14e7404","modified":1685257445628,"created":1685256992320,"url":"http://localhost:3333/auth/signin","name":"New Request","description":"","method":"POST","body":{"mimeType":"application/x-www-form-urlencoded","params":[{"id":"pair_cf50e068aea347b69593559c757731c9","name":"login","value":"leshaxgmail.com","description":""},{"id":"pair_8e0f4f10bbf34bed901f09a060458345","name":"password","value":"123","description":""}]},"parameters":[],"headers":[{"name":"Content-Type","value":"application/x-www-form-urlencoded"}],"authentication":{},"metaSortKey":-1685256992320,"isPrivate":false,"settingStoreCookies":true,"settingSendCookies":true,"settingDisableRenderRequestBody":false,"settingEncodeUrl":true,"settingRebuildPath":true,"settingFollowRedirects":"global","_type":"request"},{"_id":"wrk_8e8c71d4ad08446faea254f3d14e7404","parentId":null,"modified":1685256951588,"created":1685256951588,"name":"New Document","description":"","scope":"design","_type":"workspace"},{"_id":"req_71f1ce02d5044426bb510ee14fa264dd","parentId":"wrk_7183b84fd16a4cba8ff487b5e0f60874","modified":1685876581546,"created":1685430634623,"url":"http://localhost:3333/auth/signup","name":"Sign Up","description":"","method":"POST","body":{"mimeType":"application/x-www-form-urlencoded","params":[{"id":"pair_9de881930f6f48c38704b54b4ec03547","name":"email","value":"leshax@gmail.com","description":""},{"id":"pair_d2276f78bf9448edbef03ab0c2fa8a20","name":"password","value":"123","description":""}]},"parameters":[],"headers":[{"name":"Content-Type","value":"application/x-www-form-urlencoded"}],"authentication":{},"metaSortKey":-1685430634623,"isPrivate":false,"settingStoreCookies":true,"settingSendCookies":true,"settingDisableRenderRequestBody":false,"settingEncodeUrl":true,"settingRebuildPath":true,"settingFollowRedirects":"global","_type":"request"},{"_id":"wrk_7183b84fd16a4cba8ff487b5e0f60874","parentId":null,"modified":1685430634619,"created":1685430634619,"name":"New Document","description":"","scope":"design","_type":"workspace"},{"_id":"req_f5a856b6c1a849cf948bd8b38a45fb67","parentId":"wrk_7183b84fd16a4cba8ff487b5e0f60874","modified":1685876597529,"created":1685437881741,"url":"http://localhost:3333/auth/deleteAll","name":"Delete All","description":"","method":"GET","body":{},"parameters":[],"headers":[],"authentication":{},"metaSortKey":-1685437881741,"isPrivate":false,"settingStoreCookies":true,"settingSendCookies":true,"settingDisableRenderRequestBody":false,"settingEncodeUrl":true,"settingRebuildPath":true,"settingFollowRedirects":"global","_type":"request"},{"_id":"req_981c2f3098034eaa9311f16b70c64f9e","parentId":"wrk_7183b84fd16a4cba8ff487b5e0f60874","modified":1685876604259,"created":1685876530266,"url":"http://localhost:3333/auth/signin","name":"Sign in","description":"","method":"POST","body":{},"parameters":[],"headers":[],"authentication":{},"metaSortKey":-1685876530266,"isPrivate":false,"settingStoreCookies":true,"settingSendCookies":true,"settingDisableRenderRequestBody":false,"settingEncodeUrl":true,"settingRebuildPath":true,"settingFollowRedirects":"global","_type":"request"},{"_id":"env_5ed8df36c96365a444291cccea0ec36d80734d31","parentId":"wrk_8e8c71d4ad08446faea254f3d14e7404","modified":1685256951590,"created":1685256951590,"name":"Base Environment","data":{},"dataPropertyOrder":null,"color":null,"isPrivate":false,"metaSortKey":1685256951590,"_type":"environment"},{"_id":"jar_5ed8df36c96365a444291cccea0ec36d80734d31","parentId":"wrk_8e8c71d4ad08446faea254f3d14e7404","modified":1685256951591,"created":1685256951591,"name":"Default Jar","cookies":[],"_type":"cookie_jar"},{"_id":"spc_b2f48a34dff5499fa3c913812c131339","parentId":"wrk_8e8c71d4ad08446faea254f3d14e7404","modified":1685810410967,"created":1685256951588,"fileName":"New Document","contents":"","contentType":"yaml","_type":"api_spec"},{"_id":"uts_4642fbd7b4b94a9fb7221b7d3399dbab","parentId":"wrk_8e8c71d4ad08446faea254f3d14e7404","modified":1685256951592,"created":1685256951592,"name":"Example Test Suite","_type":"unit_test_suite"},{"_id":"env_71c69505c041bbb28cf6984c1ca09daf02657713","parentId":"wrk_7183b84fd16a4cba8ff487b5e0f60874","modified":1685430634621,"created":1685430634621,"name":"Base Environment","data":{},"dataPropertyOrder":null,"color":null,"isPrivate":false,"metaSortKey":1685430634621,"_type":"environment"},{"_id":"jar_71c69505c041bbb28cf6984c1ca09daf02657713","parentId":"wrk_7183b84fd16a4cba8ff487b5e0f60874","modified":1685430634622,"created":1685430634622,"name":"Default Jar","cookies":[],"_type":"cookie_jar"},{"_id":"spc_3717ad9727734b4a97c783e6540ee611","parentId":"wrk_7183b84fd16a4cba8ff487b5e0f60874","modified":1685810410971,"created":1685430634620,"fileName":"New Document","contents":"","contentType":"yaml","_type":"api_spec"},{"_id":"uts_a32eb80588f0401aa3ae91ae5ae9b17a","parentId":"wrk_7183b84fd16a4cba8ff487b5e0f60874","modified":1685430634624,"created":1685430634624,"name":"Example Test Suite","_type":"unit_test_suite"},{"_id":"env_986cd001145b4d7badb05955745b0c95","parentId":"env_71c69505c041bbb28cf6984c1ca09daf02657713","modified":1685876763702,"created":1685876715678,"name":"Develop","data":{},"dataPropertyOrder":{},"color":"#ff0000","isPrivate":false,"metaSortKey":1685876715678,"_type":"environment"}]}